render_engine_markdown/__init__.py
render_engine_markdown-2023.12.1.dist-info/LICENSE
render_engine_markdown-2023.12.1.dist-info/METADATA
render_engine_markdown-2023.12.1.dist-info/WHEEL
render_engine_markdown-2023.12.1.dist-info/top_level.txt
render_engine_markdown-2023.12.1.dist-info/RECORD
