Metadata-Version: 2.1
Name: render-engine-markdown
Version: 2023.12.1
Summary: Markdown Parser for Render Engine
Project-URL: homepage, https://github.com/kjaymiller/render_engine/
Project-URL: repository, https://github.com/kjaymiller/render_engine/
Project-URL: documentation, https://render-engine.readthedocs.io/en/latest/
Requires-Python: >=3.10
License-File: LICENSE
Requires-Dist: markdown2
Requires-Dist: render-engine-parser
Provides-Extra: dev
Requires-Dist: pytest ; extra == 'dev'
Requires-Dist: pytest-cov ; extra == 'dev'
Requires-Dist: ruff ; extra == 'dev'
